metroconv/__init__.py
metroconv/csv_utils.py
metroconv/transactions.py
metroconv/scripts/__init__.py
metroconv/scripts/main.py
metroconv-1.0b1.dist-info/LICENSE.txt
metroconv-1.0b1.dist-info/METADATA
metroconv-1.0b1.dist-info/WHEEL
metroconv-1.0b1.dist-info/entry_points.txt
metroconv-1.0b1.dist-info/top_level.txt
metroconv-1.0b1.dist-info/RECORD
